{
  "id": "c97cf7e5-926f-4cbf-bd98-624de8cd49d9",
  "prevId": "00000000-0000-0000-0000-000000000000",
  "version": "7",
  "dialect": "postgresql",
  "tables": {
    "public.contract_details": {
      "name": "contract_details",
      "schema": "",
      "columns": {
        "id": {
          "name": "id",
          "type": "uuid",
          "primaryKey": true,
          "notNull": true,
          "default": "gen_random_uuid()"
        },
        "payment_link_id": {
          "name": "payment_link_id",
          "type": "uuid",
          "primaryKey": false,
          "notNull": true
        },
        "contract_terms": {
          "name": "contract_terms",
          "type": "text",
          "primaryKey": false,
          "notNull": false
        },
        "contract_file_url": {
          "name": "contract_file_url",
          "type": "varchar(500)",
          "primaryKey": false,
          "notNull": false
        },
        "arbitrator_address": {
          "name": "arbitrator_address",
          "type": "varchar(42)",
          "primaryKey": false,
          "notNull": false
        },
        "arbitration_fee": {
          "name": "arbitration_fee",
          "type": "numeric(18, 8)",
          "primaryKey": false,
          "notNull": false
        },
        "created_at": {
          "name": "created_at",
          "type": "timestamp",
          "primaryKey": false,
          "notNull": true,
          "default": "now()"
        }
      },
      "indexes": {},
      "foreignKeys": {
        "contract_details_payment_link_id_payment_links_id_fk": {
          "name": "contract_details_payment_link_id_payment_links_id_fk",
          "tableFrom": "contract_details",
          "tableTo": "payment_links",
          "columnsFrom": [
            "payment_link_id"
          ],
          "columnsTo": [
            "id"
          ],
          "onDelete": "no action",
          "onUpdate": "no action"
        }
      },
      "compositePrimaryKeys": {},
      "uniqueConstraints": {},
      "policies": {},
      "checkConstraints": {},
      "isRLSEnabled": false
    },
    "public.payment_links": {
      "name": "payment_links",
      "schema": "",
      "columns": {
        "id": {
          "name": "id",
          "type": "uuid",
          "primaryKey": true,
          "notNull": true,
          "default": "gen_random_uuid()"
        },
        "short_id": {
          "name": "short_id",
          "type": "varchar(12)",
          "primaryKey": false,
          "notNull": true
        },
        "creator_address": {
          "name": "creator_address",
          "type": "varchar(42)",
          "primaryKey": false,
          "notNull": true
        },
        "link_type": {
          "name": "link_type",
          "type": "varchar(10)",
          "primaryKey": false,
          "notNull": true
        },
        "target_address": {
          "name": "target_address",
          "type": "varchar(42)",
          "primaryKey": false,
          "notNull": false
        },
        "amount": {
          "name": "amount",
          "type": "numeric(18, 8)",
          "primaryKey": false,
          "notNull": true
        },
        "token": {
          "name": "token",
          "type": "varchar(10)",
          "primaryKey": false,
          "notNull": true
        },
        "chain": {
          "name": "chain",
          "type": "varchar(20)",
          "primaryKey": false,
          "notNull": true
        },
        "escrow_type": {
          "name": "escrow_type",
          "type": "varchar(10)",
          "primaryKey": false,
          "notNull": true
        },
        "escrow_hours": {
          "name": "escrow_hours",
          "type": "integer",
          "primaryKey": false,
          "notNull": false
        },
        "description": {
          "name": "description",
          "type": "text",
          "primaryKey": false,
          "notNull": false
        },
        "status": {
          "name": "status",
          "type": "varchar(20)",
          "primaryKey": false,
          "notNull": true,
          "default": "'created'"
        },
        "accepted_by": {
          "name": "accepted_by",
          "type": "varchar(42)",
          "primaryKey": false,
          "notNull": false
        },
        "accepted_at": {
          "name": "accepted_at",
          "type": "timestamp",
          "primaryKey": false,
          "notNull": false
        },
        "yellow_channel_id": {
          "name": "yellow_channel_id",
          "type": "varchar(255)",
          "primaryKey": false,
          "notNull": false
        },
        "nitrolite_transaction_hash": {
          "name": "nitrolite_transaction_hash",
          "type": "varchar(66)",
          "primaryKey": false,
          "notNull": false
        },
        "yellow_network_status": {
          "name": "yellow_network_status",
          "type": "varchar(20)",
          "primaryKey": false,
          "notNull": false
        },
        "custom_contract": {
          "name": "custom_contract",
          "type": "boolean",
          "primaryKey": false,
          "notNull": false,
          "default": false
        },
        "dispute_resolution": {
          "name": "dispute_resolution",
          "type": "boolean",
          "primaryKey": false,
          "notNull": false,
          "default": false
        },
        "created_at": {
          "name": "created_at",
          "type": "timestamp",
          "primaryKey": false,
          "notNull": true,
          "default": "now()"
        },
        "expires_at": {
          "name": "expires_at",
          "type": "timestamp",
          "primaryKey": false,
          "notNull": false
        },
        "updated_at": {
          "name": "updated_at",
          "type": "timestamp",
          "primaryKey": false,
          "notNull": true,
          "default": "now()"
        },
        "completed_at": {
          "name": "completed_at",
          "type": "timestamp",
          "primaryKey": false,
          "notNull": false
        }
      },
      "indexes": {},
      "foreignKeys": {},
      "compositePrimaryKeys": {},
      "uniqueConstraints": {
        "payment_links_short_id_unique": {
          "name": "payment_links_short_id_unique",
          "nullsNotDistinct": false,
          "columns": [
            "short_id"
          ]
        }
      },
      "policies": {},
      "checkConstraints": {},
      "isRLSEnabled": false
    },
    "public.yellow_channels": {
      "name": "yellow_channels",
      "schema": "",
      "columns": {
        "id": {
          "name": "id",
          "type": "uuid",
          "primaryKey": true,
          "notNull": true,
          "default": "gen_random_uuid()"
        },
        "payment_link_id": {
          "name": "payment_link_id",
          "type": "uuid",
          "primaryKey": false,
          "notNull": true
        },
        "channel_id": {
          "name": "channel_id",
          "type": "varchar(255)",
          "primaryKey": false,
          "notNull": true
        },
        "participant_a": {
          "name": "participant_a",
          "type": "varchar(42)",
          "primaryKey": false,
          "notNull": true
        },
        "participant_b": {
          "name": "participant_b",
          "type": "varchar(42)",
          "primaryKey": false,
          "notNull": true
        },
        "asset": {
          "name": "asset",
          "type": "varchar(10)",
          "primaryKey": false,
          "notNull": true
        },
        "total_amount": {
          "name": "total_amount",
          "type": "numeric(18, 8)",
          "primaryKey": false,
          "notNull": true
        },
        "status": {
          "name": "status",
          "type": "varchar(20)",
          "primaryKey": false,
          "notNull": true,
          "default": "'active'"
        },
        "created_at": {
          "name": "created_at",
          "type": "timestamp",
          "primaryKey": false,
          "notNull": true,
          "default": "now()"
        },
        "settled_at": {
          "name": "settled_at",
          "type": "timestamp",
          "primaryKey": false,
          "notNull": false
        }
      },
      "indexes": {},
      "foreignKeys": {
        "yellow_channels_payment_link_id_payment_links_id_fk": {
          "name": "yellow_channels_payment_link_id_payment_links_id_fk",
          "tableFrom": "yellow_channels",
          "tableTo": "payment_links",
          "columnsFrom": [
            "payment_link_id"
          ],
          "columnsTo": [
            "id"
          ],
          "onDelete": "no action",
          "onUpdate": "no action"
        }
      },
      "compositePrimaryKeys": {},
      "uniqueConstraints": {
        "yellow_channels_channel_id_unique": {
          "name": "yellow_channels_channel_id_unique",
          "nullsNotDistinct": false,
          "columns": [
            "channel_id"
          ]
        }
      },
      "policies": {},
      "checkConstraints": {},
      "isRLSEnabled": false
    }
  },
  "enums": {},
  "schemas": {},
  "sequences": {},
  "roles": {},
  "policies": {},
  "views": {},
  "_meta": {
    "columns": {},
    "schemas": {},
    "tables": {}
  }
}